vnpay/__init__.py
vnpay/admin.py
vnpay/api_urls.py
vnpay/apps.py
vnpay/models.py
vnpay/payment_test.py
vnpay/utils.py
vnpay/api/__init__.py
vnpay/api/payment_ipn.py
vnpay/api/payment_return.py
vnpay/api/payment_url.py
vnpay/migrations/0001_initial.py
vnpay/migrations/__init__.py
vnpay/templates/__init__.py
vnpay/templates/vnpay/base_layout.html
vnpay/templates/vnpay/payment.html
vnpay/templates/vnpay/payment_return.html
django_vnpay-0.0.19.dist-info/LICENSE
django_vnpay-0.0.19.dist-info/METADATA
django_vnpay-0.0.19.dist-info/WHEEL
django_vnpay-0.0.19.dist-info/top_level.txt
django_vnpay-0.0.19.dist-info/RECORD
