Metadata-Version: 2.1
Name: django-vnpay
Version: 0.0.19
Summary: A quick package for integrating Vnpay payment gateway.
Author-email: Son Lam <son.lg@eoh.io>
License: Apache License
Project-URL: Homepage, https://github.com/laughlamz/django-vnpay
Keywords: django,vnpay
Classifier: Programming Language :: Python :: 3
Classifier: License :: OSI Approved :: MIT License
Classifier: Operating System :: OS Independent
Requires-Python: >=3.10
License-File: LICENSE
Requires-Dist: django >=4.0.0
Requires-Dist: djangorestframework >=3.12.4
Requires-Dist: django-ipware >=4.0.0
Provides-Extra: dev
Requires-Dist: bumpver ; extra == 'dev'
Requires-Dist: poetry ; extra == 'dev'
Requires-Dist: pip-tools ; extra == 'dev'
Requires-Dist: pytest ; extra == 'dev'
